trt2onnx/__init__.py
trt2onnx/trt2onnx.py
trt2onnx/core/__init__.py
trt2onnx/core/convert.py
trt2onnx/core/element.py
trt2onnx/core/graph.py
trt2onnx-0.0.1.dist-info/LICENSE
trt2onnx-0.0.1.dist-info/METADATA
trt2onnx-0.0.1.dist-info/WHEEL
trt2onnx-0.0.1.dist-info/top_level.txt
trt2onnx-0.0.1.dist-info/RECORD
