Metadata-Version: 2.1
Name: trt2onnx
Version: 0.0.1
Summary: A tools convert tensorrt engine to a fake onnx
Author: triplemu
Author-email: gpu@163.com
Classifier: Programming Language :: Python :: 3
Classifier: License :: OSI Approved :: MIT License
Classifier: Operating System :: OS Independent
Requires-Python: >=3
License-File: LICENSE
Requires-Dist: numpy
Requires-Dist: onnx
